[{"building": "building 1", "lat": 47.6413103, "lng": -122.1255952, "type": "coconut"}, {"building": "building 2", "lat": 47.6406281, "lng": -122.1262172, "type": "coconut"}, {"building": "building 3", "lat": 47.64057239999999, "lng": -122.1248905, "type": "coconut"}, {"building": "building 4", "lat": 47.6399956, "lng": -122.1256411, "type": "coconut"}, {"building": "building 5", "lat": 47.63923579999999, "lng": -122.1251225, "type": "coconut"}, {"building": "building 6", "lat": 47.6392201, "lng": -122.1261176, "type": "coconut"}, {"building": "building 8", "lat": 47.64060349999999, "lng": -122.1276643, "type": "coconut"}, {"building": "building 9", "lat": 47.6396478, "lng": -122.1283445, "type": "coconut"}, {"building": "building 10", "lat": 47.6386289, "lng": -122.1276867, "type": "coconut"}, {"building": "building 11", "lat": 47.6397383, "lng": -122.1314277, "type": "coconut"}, {"building": "building 19", "lat": 47.6430348, "lng": -122.1313097, "type": "coconut"}, {"building": "building 21", "lat": 47.64536409999999, "lng": -122.1278175, "type": "coconut"}, {"building": "building 22", "lat": 47.6372222, "lng": -122.1359968, "type": "coconut"}, {"building": "building 25", "lat": 47.645136, "lng": -122.130939, "type": "coconut"}, {"building": "building 26", "lat": 47.63783340000001, "lng": -122.1302309, "type": "coconut"}, {"building": "building 27", "lat": 47.6361219, "lng": -122.1302545, "type": "coconut"}, {"building": "building 28", "lat": 47.6363529, "lng": -122.1284894, "type": "coconut"}, {"building": "building 30", "lat": 47.6449778, "lng": -122.1222083, "type": "coconut"}, {"building": "building 31", "lat": 47.6437329, "lng": -122.1223912, "type": "coconut"}, {"building": "building 32", "lat": 47.6428627, "lng": -122.1214217, "type": "coconut"}, {"building": "building 34", "lat": 47.6440131, "lng": -122.1257108, "type": "coconut"}, {"building": "building 35", "lat": 47.6450651, "lng": -122.1257584, "type": "coconut"}, {"building": "building 36", "lat": 47.6413509, "lng": -122.1237998, "type": "coconut"}, {"building": "building 37", "lat": 47.6382279, "lng": -122.1258687, "type": "coconut"}, {"building": "building 40", "lat": 47.63636899999999, "lng": -122.133132, "type": "coconut"}, {"building": "building 41", "lat": 47.6378801, "lng": -122.132982, "type": "coconut"}, {"building": "building 111", "lat": 47.640362, "lng": -122.137651, "type": "coconut"}, {"building": "advanta A", "lat": 47.58358459999999, "lng": -122.1308291, "type": "coconut"}, {"building": "advanta B", "lat": 47.5837438, "lng": -122.1274417, "type": "coconut"}, {"building": "advanta C", "lat": 47.5835219, "lng": -122.1297466, "type": "coconut"}, {"building": "samm C", "lat": 47.5560924, "lng": -122.0495477, "type": "coconut"}, {"building": "samm D", "lat": 47.5556462, "lng": -122.0494794, "type": "coconut"}, {"building": "building 5", "lat": 47.63923579999999, "lng": -122.1251225, "type": "latte"}, {"building": "building 6", "lat": 47.6392201, "lng": -122.1261176, "type": "latte"}, {"building": "building 16", "lat": 47.6431213, "lng": -122.1290781, "type": "latte"}, {"building": "building 27", "lat": 47.6361219, "lng": -122.1302545, "type": "latte"}, {"building": "building 28", "lat": 47.6363529, "lng": -122.1284894, "type": "latte"}, {"building": "building 111", "lat": 47.640362, "lng": -122.137651, "type": "latte"}, {"building": "building 92", "lat": 47.64235739999999, "lng": -122.1371521, "type": "coconut"}, {"building": "new england (8th floor)", "lat": 42.3625962, "lng": -71.0854828, "type": "coconut"}]